examples/__init__.py
examples/basic_usage.py
examples/marketing_roi.py
examples/performance_reports.py
examples/revenue_analysis.py
servicetitan_pyapi/__init__.py
servicetitan_pyapi/auth.py
servicetitan_pyapi/base.py
servicetitan_pyapi/clients/__init__.py
servicetitan_pyapi/clients/appointments.py
servicetitan_pyapi/clients/bookings.py
servicetitan_pyapi/clients/calls.py
servicetitan_pyapi/clients/customers.py
servicetitan_pyapi/clients/estimates.py
servicetitan_pyapi/clients/invoices.py
servicetitan_pyapi/clients/jobs.py
servicetitan_pyapi/clients/leads.py
servicetitan_pyapi/clients/locations.py
servicetitan_pyapi/clients/marketing.py
servicetitan_pyapi/clients/marketing_ads.py
servicetitan_pyapi/clients/settings.py
servicetitan_pyapi/models/__init__.py
servicetitan_pyapi/models/responses.py
servicetitan_pyapi/utils/__init__.py
servicetitan_pyapi/utils/exceptions.py
servicetitan_pyapi/utils/helpers.py
servicetitan_pyapi-1.0.0.dist-info/licenses/LICENSE
servicetitan_pyapi-1.0.0.dist-info/METADATA
servicetitan_pyapi-1.0.0.dist-info/WHEEL
servicetitan_pyapi-1.0.0.dist-info/top_level.txt
servicetitan_pyapi-1.0.0.dist-info/RECORD
