Metadata-Version: 2.4
Name: servicetitan-pyapi
Version: 1.0.0
Summary: A comprehensive Python client library for the ServiceTitan API
Home-page: https://github.com/n90-co/servicetitan-pyapi
Author: Brian Handrigan
Author-email: brian@n90.co
Project-URL: Bug Reports, https://github.com/n90-co/servicetitan-pyapi/issues
Project-URL: Source, https://github.com/n90-co/servicetitan-pyapi
Project-URL: Documentation, https://github.com/n90-co/servicetitan-pyapi#readme
Keywords: servicetitan api client hvac plumbing field-service crm
Classifier: Development Status :: 5 - Production/Stable
Classifier: Intended Audience :: Developers
Classifier: Topic :: Software Development :: Libraries :: Python Modules
Classifier: Topic :: Internet :: WWW/HTTP :: Dynamic Content
Classifier: Topic :: Office/Business
Classifier: License :: OSI Approved :: MIT License
Classifier: Programming Language :: Python :: 3
Classifier: Programming Language :: Python :: 3.8
Classifier: Programming Language :: Python :: 3.9
Classifier: Programming Language :: Python :: 3.10
Classifier: Programming Language :: Python :: 3.11
Classifier: Programming Language :: Python :: 3.12
Classifier: Operating System :: OS Independent
Requires-Python: >=3.8
License-File: LICENSE
Requires-Dist: requests>=2.28.0
Requires-Dist: python-dateutil>=2.8.2
Provides-Extra: dev
Requires-Dist: pytest>=7.0.0; extra == "dev"
Requires-Dist: pytest-mock; extra == "dev"
Requires-Dist: requests-mock; extra == "dev"
Requires-Dist: pytest-cov>=3.0.0; extra == "dev"
Requires-Dist: black>=22.0.0; extra == "dev"
Requires-Dist: isort>=5.0.0; extra == "dev"
Requires-Dist: flake8>=4.0.0; extra == "dev"
Requires-Dist: mypy>=0.991; extra == "dev"
Requires-Dist: bandit>=1.7.0; extra == "dev"
Requires-Dist: safety>=2.0.0; extra == "dev"
Provides-Extra: notebooks
Requires-Dist: jupyter>=1.0.0; extra == "notebooks"
Requires-Dist: pandas>=1.4.0; extra == "notebooks"
Requires-Dist: matplotlib>=3.5.0; extra == "notebooks"
Provides-Extra: testing
Requires-Dist: pytest>=7.0.0; extra == "testing"
Requires-Dist: pytest-mock; extra == "testing"
Requires-Dist: requests-mock; extra == "testing"
Requires-Dist: pytest-cov>=3.0.0; extra == "testing"
Requires-Dist: pytest-xdist; extra == "testing"
Dynamic: author
Dynamic: author-email
Dynamic: classifier
Dynamic: description
Dynamic: description-content-type
Dynamic: home-page
Dynamic: keywords
Dynamic: license-file
Dynamic: project-url
Dynamic: provides-extra
Dynamic: requires-dist
Dynamic: requires-python
Dynamic: summary
